impecunious_sql_etl/__init__.py
impecunious_sql_etl/auth.py
impecunious_sql_etl/cli.py
impecunious_sql_etl/config.py
impecunious_sql_etl/etl_log.py
impecunious_sql_etl/extract.py
impecunious_sql_etl/load.py
impecunious_sql_etl/transform.py
impecunious_sql_etl/utils.py
impecunious_sql_etl-0.1.4.dist-info/METADATA
impecunious_sql_etl-0.1.4.dist-info/WHEEL
impecunious_sql_etl-0.1.4.dist-info/entry_points.txt
impecunious_sql_etl-0.1.4.dist-info/top_level.txt
impecunious_sql_etl-0.1.4.dist-info/RECORD
