Metadata-Version: 2.4
Name: Impecunious-sql-etl
Version: 0.1.4
Summary: Parallel, config-driven SQL Server ETL tool
Author: Impecunious
License-Expression: MIT
Keywords: etl,sql-server,data-engineering
Classifier: Programming Language :: Python :: 3
Classifier: Operating System :: OS Independent
Requires-Python: >=3.9
Requires-Dist: pandas
Requires-Dist: pyarrow
Requires-Dist: sqlalchemy
Requires-Dist: pyodbc
Requires-Dist: pyyaml
Requires-Dist: click
